Metadata-Version: 1.0
Name: persistedrmq3
Version: 0.0.13
Summary: A simple MQ based on Redis pubsub, but won't lose message version 3
Home-page: https://github.com/ipconfiger/persistedRMQ3
Author: Alexander.Li
Author-email: superpowerlee@gmail.com
License: GNU General Public License v3.0
Keywords: MQ Redis Pubsub Persisted
Platform: UNKNOWN
